ultrasav/__init__.py
ultrasav/_add_cases.py
ultrasav/_data.py
ultrasav/_make_dummy.py
ultrasav/_merge_data.py
ultrasav/_merge_meta.py
ultrasav/_metadata.py
ultrasav/_read_files.py
ultrasav/_set_value_labels.py
ultrasav/_write_files.py
ultrasav/datacfg/__init__.py
ultrasav/datacfg/class_config.py
ultrasav/datacfg/constants.py
ultrasav/datacfg/def_clean_data.py
ultrasav/datacfg/def_load_config.py
ultrasav/metaman/__init__.py
ultrasav/metaman/_color_schemes.py
ultrasav/metaman/_describe.py
ultrasav/metaman/_detect_variable_type.py
ultrasav/metaman/_get_meta.py
ultrasav/metaman/_make_datamap.py
ultrasav/metaman/_make_labels.py
ultrasav/metaman/_map_engine.py
ultrasav/metaman/_map_to_excel.py
ultrasav/metaman/_write_excel_engine.py
ultrasav-0.2.13.dist-info/WHEEL
ultrasav-0.2.13.dist-info/METADATA
ultrasav-0.2.13.dist-info/RECORD
