Metadata-Version: 2.3
Name: ultrasav
Version: 0.2.13
Summary: A Python package for working with SPSS/SAV files with two-track architecture separating data and metadata operations
Keywords: spss,spss labels,spss files,sav files,sav,statistics,data-science,data-processing,survey-data,metadata,spss metadata,pyreadstat,dataframe-agnostic,polars,pandas,read spss,read sav,write spss,write sav,merge spss,merge sav,datamap,spss-datamap,validation,data-quality,tidyspss,metaprinter
Author: Albert Li
License: MIT
Requires-Dist: pandas>=2.2.0
Requires-Dist: polars>=1.3.0
Requires-Dist: pyreadstat>=1.3.2
Requires-Dist: narwhals>=2.11.0
Requires-Dist: openpyxl>=3.0.0
Requires-Dist: xlsxwriter>=3.1.0
Requires-Dist: colocate>=0.1.1
Requires-Dist: ultrasav[excel,dev,docs] ; extra == 'all'
Requires-Dist: pytest>=7.0.0 ; extra == 'dev'
Requires-Dist: pytest-cov>=4.0.0 ; extra == 'dev'
Requires-Dist: black>=23.0.0 ; extra == 'dev'
Requires-Dist: ruff>=0.1.0 ; extra == 'dev'
Requires-Dist: mypy>=1.0.0 ; extra == 'dev'
Requires-Dist: pre-commit>=3.0.0 ; extra == 'dev'
Requires-Dist: sphinx>=6.0.0 ; extra == 'docs'
Requires-Dist: sphinx-rtd-theme>=1.0.0 ; extra == 'docs'
Requires-Dist: myst-parser>=1.0.0 ; extra == 'docs'
Requires-Dist: fastexcel>=0.9.0 ; extra == 'excel'
Maintainer: Albert Li
Requires-Python: >=3.12
Project-URL: Homepage, https://github.com/albertxli/ultrasav
Project-URL: Documentation, https://ultrasav.readthedocs.io
Project-URL: Changelog, https://github.com/albertxli/ultrasav/blob/main/CHANGELOG.md
Provides-Extra: all
Provides-Extra: dev
Provides-Extra: docs
Provides-Extra: excel
